amitools/AmiTool.py
amitools/__init__.py
amitool-0.1.5.dist-info/METADATA
amitool-0.1.5.dist-info/WHEEL
amitool-0.1.5.dist-info/top_level.txt
amitool-0.1.5.dist-info/RECORD
