Metadata-Version: 2.1
Name: amitool
Version: 0.1.5
Summary: create session and redis
Home-page: https://github.com/ccmldl/AmiTools
Author: ccmldl
Author-email: 1738407610@qq.com
License: UNKNOWN
Platform: UNKNOWN
Requires-Dist: loguru (==0.5.3)
Requires-Dist: pyodbc (==4.0.30)
Requires-Dist: redis (==3.5.3)
Requires-Dist: SQLAlchemy (==1.3.23)
